uids/__init__.py
uids/ULID/__init__.py
uids/ULID/test.py
uids/utils/__init__.py
uids/utils/base32.py
uids/utils/baseinterface.py
uids/utils/misc.py
uids/utils/system_checks.py
uids-0.0.2.dist-info/LICENSE
uids-0.0.2.dist-info/METADATA
uids-0.0.2.dist-info/WHEEL
uids-0.0.2.dist-info/top_level.txt
uids-0.0.2.dist-info/RECORD
